{ "banner":[{"img":"images/1.jpg","url":"https://img22.iblimg.com/market-3/images/activity/1492715753.jpg"},
    {"img":"images/2.jpg","url":"https://img22.iblimg.com/market-3/images/activity/294521100.jpg"},
    {"img":"images/3.jpg","url":"https://img22.iblimg.com/market-3/images/activity/294521100.jpg"},
    {"img":"images/4.jpg","url":"https://img22.iblimg.com/market-3/images/activity/294521100.jpg"},
    {"img":"images/5.jpg","url":"https://img22.iblimg.com/market-3/images/activity/294521100.jpg"}],
"sideNav":[
    {"Title":"百联进口 全球购",
        "child":[{"title":"美妆护肤 >"},{"title":"面膜"},{"title":"乳液/面霜"},{"title":"护肤套装"},{"title":"眼部护"},
             {"title":"面部精华"},{"title":"美容仪"},{"title":"洁面"},{"title":"卸妆"},{"title":"彩妆"},{"title":"香水"},{"title":"男士护肤"},
             {"title":"口红"},{"title":"美妆工具"},
             {"title":"个人护理 >"},{"title":"洗发水"},{"title":"护发素"},{"title":"沐浴露"},{"title":"漱口水"},{"title":"牙膏"},{"title":"身体乳"}
             ,{"title":"护手霜"},{"title":"身体护理"},{"title":"卫生巾"},{"title":" "},{"title":" "},{"title":" "},{"title":" "},
             {"title":"进口美食 >"},{"title":"坚果"},{"title":"果干"},{"title":"膨化"},{"title":"糖果"},{"title":"海苔"},{"title":"饼干"},{"title":"曲奇"}
             ,{"title":"曲奇"},{"title":"橄榄油"},{"title":"泡面"},{"title":"蜂蜜"},{"title":" "},{"title":" "},{"title":"乳品冲饮 >"},{"title":"牛奶"},{"title":"全脂"},{"title":"低脂"}
             ,{"title":"饮料"},{"title":"成人奶粉"},{"title":"营养谷物"},{"title":"咖啡"},{"title":"水"},{"title":"碳酸"},{"title":"葡萄酒"},{"title":"啤酒"}
             ,{"title":"洋酒"},{"title":" "},{"title":"家庭清洁 >"},{"title":"洗衣液"},{"title":"洗衣凝珠"},{"title":"洗衣粉"},{"title":"洗洁精"}
             ,{"title":"油污净"},{"title":"多用途清洁剂"},{"title":"马桶清洁"},{"title":"卫浴清洁剂"},{"title":" "},{"title":" "},{"title":" "},{"title":" "},{"title":" "},{"title":"进口母婴 >"},{"title":"奶粉"}
             ,{"title":"辅食"},{"title":"纸尿裤"},{"title":"奶瓶奶嘴"},{"title":"水杯餐具"},{"title":"洗发沐浴"},{"title":"宝宝护肤"},{"title":"口腔清洁"}
             ,{"title":"手推车"},{"title":"安全座椅"},{"title":" "},{"title":" "},{"title":" "},{"title":"品质家具 >"},{"title":"吸尘器"},{"title":"咖啡机"},{"title":"保温杯"}
             ,{"title":"榨汁机"},{"title":"滤水壶"},{"title":"锅具"},{"title":"刀具"},{"title":"乳胶枕"},{"title":" "},{"title":" "},{"title":" "},{"title":" "},{"title":" "},{"title":"鞋靴箱包 >"},{"title":"GUCCI"}
             ,{"title":"COACH"},{"title":"MK"},{"title":"MCM"},{"title":"KENZO"},{"title":"FURLA"},{"title":"LONGCHAMP"},{"title":" "},{"title":" "},{"title":" "},{"title":" "},{"title":" "},{"title":" "},{"title":"腕表饰品 >"}
             ,{"title":"雷朋"},{"title":"Cition"},{"title":"Pandora"},{"title":"DW"},{"title":"CASIO"},{"title":"施华洛世奇"}
            ],
             "rightImg":["397669452.jpg","43327109.jpg"]},
    {"Title":"生鲜食品",
    "child":[{"title":"美妆护肤 >"},{"title":"面膜"},{"title":"乳液/面霜"},{"title":"护肤套装"},{"title":"眼部护"},
        {"title":"面部精华"},{"title":"美容仪"},{"title":"洁面"},{"title":"卸妆"},{"title":"彩妆"},{"title":"香水"},{"title":"男士护肤"},
        {"title":"口红"},{"title":"美妆工具"},{"title":"美妆护肤 >"},{"title":"美妆护肤 >"}],"rightImg":["1648698545.jpg","654041603.jpg"]
},
{"Title":"食品粮油 酒水冲饮",
    "child":[{"title":"美妆护肤 >"},{"title":"面膜"},{"title":"乳液/面霜"},{"title":"护肤套装"},{"title":"眼部护"},
        {"title":"面部精华"},{"title":"美容仪"},{"title":"洁面"},{"title":"卸妆"},{"title":"彩妆"},{"title":"香水"},{"title":"男士护肤"},
        {"title":"口红"},{"title":"美妆工具"},{"title":"美妆护肤 >"},{"title":"美妆护肤 >"}],"rightImg":["1410156029.jpg","1289477667.jpg"]
},
{"Title":"美容护理",
    "child":[{"title":"美妆护肤 >"},{"title":"面膜"},{"title":"乳液/面霜"},{"title":"护肤套装"},{"title":"眼部护"},
        {"title":"面部精华"},{"title":"美容仪"},{"title":"洁面"},{"title":"卸妆"},{"title":"彩妆"},{"title":"香水"},{"title":"男士护肤"},
        {"title":"口红"},{"title":"美妆工具"},{"title":"美妆护肤 >"},{"title":"美妆护肤 >"}],"rightImg":["303067987.jpg","1433236921.jpg"]
},
{"Title":"餐厨用具 家居家装",
    "child":[{"title":"美妆护肤 >"},{"title":"面膜"},{"title":"乳液/面霜"},{"title":"护肤套装"},{"title":"眼部护"},
        {"title":"面部精华"},{"title":"美容仪"},{"title":"洁面"},{"title":"卸妆"},{"title":"彩妆"},{"title":"香水"},{"title":"男士护肤"},
        {"title":"口红"},{"title":"美妆工具"},{"title":"美妆护肤 >"},{"title":"美妆护肤 >"}],"rightImg":["1934051378.jpg","2107487556.jpg"]
},
{"Title":"母婴玩具",
    "child":[{"title":"美妆护肤 >"},{"title":"面膜"},{"title":"乳液/面霜"},{"title":"护肤套装"},{"title":"眼部护"},
        {"title":"面部精华"},{"title":"美容仪"},{"title":"洁面"},{"title":"卸妆"},{"title":"彩妆"},{"title":"香水"},{"title":"男士护肤"},
        {"title":"口红"},{"title":"美妆工具"},{"title":"美妆护肤 >"},{"title":"美妆护肤 >"}],"rightImg":["2060757461.jpg","1232004232.jpg"]
},
{"Title":"家清 纸品 一次性",
    "child":[{"title":"美妆护肤 >"},{"title":"面膜"},{"title":"乳液/面霜"},{"title":"护肤套装"},{"title":"眼部护"},
        {"title":"面部精华"},{"title":"美容仪"},{"title":"洁面"},{"title":"卸妆"},{"title":"彩妆"},{"title":"香水"},{"title":"男士护肤"},
        {"title":"口红"},{"title":"美妆工具"},{"title":"美妆护肤 >"},{"title":"美妆护肤 >"}],"rightImg":["663959764.jpg","101989941.jpg"]
},
{"Title":"女装男装",
    "child":[{"title":"美妆护肤 >"},{"title":"面膜"},{"title":"乳液/面霜"},{"title":"护肤套装"},{"title":"眼部护"},
        {"title":"面部精华"},{"title":"美容仪"},{"title":"洁面"},{"title":"卸妆"},{"title":"彩妆"},{"title":"香水"},{"title":"男士护肤"},
        {"title":"口红"},{"title":"美妆工具"},{"title":"美妆护肤 >"},{"title":"美妆护肤 >"}],"rightImg":["1593556725.jpg","1576974182.jpg"]
},
{"Title":"鞋靴箱包 珠宝饰品",
    "child":[{"title":"美妆护肤 >"},{"title":"面膜"},{"title":"乳液/面霜"},{"title":"护肤套装"},{"title":"眼部护"},
        {"title":"面部精华"},{"title":"美容仪"},{"title":"洁面"},{"title":"卸妆"},{"title":"彩妆"},{"title":"香水"},{"title":"男士护肤"},
        {"title":"口红"},{"title":"美妆工具"},{"title":"美妆护肤 >"},{"title":"美妆护肤 >"}],"rightImg":["1611134956.jpg","477286129.jpg"]
},
{"Title":"手机数码 电脑办公",
    "child":[{"title":"美妆护肤 >"},{"title":"面膜"},{"title":"乳液/面霜"},{"title":"护肤套装"},{"title":"眼部护"},
        {"title":"面部精华"},{"title":"美容仪"},{"title":"洁面"},{"title":"卸妆"},{"title":"彩妆"},{"title":"香水"},{"title":"男士护肤"},
        {"title":"口红"},{"title":"美妆工具"},{"title":"美妆护肤 >"},{"title":"美妆护肤 >"}],"rightImg":["367190570.jpg","1626862135.jpg"]
},
{"Title":"家用电器",
    "child":[{"title":"美妆护肤 >"},{"title":"面膜"},{"title":"乳液/面霜"},{"title":"护肤套装"},{"title":"眼部护"},
        {"title":"面部精华"},{"title":"美容仪"},{"title":"洁面"},{"title":"卸妆"},{"title":"彩妆"},{"title":"香水"},{"title":"男士护肤"},
        {"title":"口红"},{"title":"美妆工具"},{"title":"美妆护肤 >"},{"title":"美妆护肤 >"}],"rightImg":["1540828056.jpg","647434064.jpg"]
},
{"Title":"运动户外 汽车用品",
    "child":[{"title":"美妆护肤 >"},{"title":"面膜"},{"title":"乳液/面霜"},{"title":"护肤套装"},{"title":"眼部护"},
        {"title":"面部精华"},{"title":"美容仪"},{"title":"洁面"},{"title":"卸妆"},{"title":"彩妆"},{"title":"香水"},{"title":"男士护肤"},
        {"title":"口红"},{"title":"美妆工具"},{"title":"美妆护肤 >"},{"title":"美妆护肤 >"}],"rightImg":["1829905795.jpg","1893731499.jpg"]
},
{"Title":"营养保健 第一医药",
    "child":[{"title":"美妆护肤 >"},{"title":"面膜"},{"title":"乳液/面霜"},{"title":"护肤套装"},{"title":"眼部护"},
        {"title":"面部精华"},{"title":"美容仪"},{"title":"洁面"},{"title":"卸妆"},{"title":"彩妆"},{"title":"香水"},{"title":"男士护肤"},
        {"title":"口红"},{"title":"美妆工具"},{"title":"美妆护肤 >"},{"title":"美妆护肤 >"}],"rightImg":["1421161552.jpg","946379458.jpg"]
},
{"Title":"礼品卡 充值 图书",
    "child":[{"title":"美妆护肤 >"},{"title":"面膜"},{"title":"乳液/面霜"},{"title":"护肤套装"},{"title":"眼部护"},
        {"title":"面部精华"},{"title":"美容仪"},{"title":"洁面"},{"title":"卸妆"},{"title":"彩妆"},{"title":"香水"},{"title":"男士护肤"},
        {"title":"口红"},{"title":"美妆工具"},{"title":"美妆护肤 >"},{"title":"美妆护肤 >"}],"rightImg":["101371635.jpg","1369952814.jpg"]
 }],
 "bigImg":[{"id":"0","img":"images/97081720_360x360.jpg"}, {"id":"1","img":"images/1053888971_360x360.jpg"},
    {"id":"2","img":"images/1503453865_360x360.jpg"}, {"id":"3","img":"images/1726666149_360x360.jpg"},
    {"id":"4","img":"images/1930144442_360x360.jpg"},{"id":"5","img":"images/1078397621_360x360.jpg"}]

}
